coverdl/__init__.py
coverdl/cache.py
coverdl/cli.py
coverdl/console.py
coverdl/cover.py
coverdl/download.py
coverdl/exceptions.py
coverdl/metadata.py
coverdl/options.py
coverdl/providers/__init__.py
coverdl/providers/apple_music.py
coverdl/providers/base.py
coverdl/providers/deezer.py
coverdl/providers/discogs.py
coverdl/providers/itunes.py
coverdl/providers/source.py
coverdl/upgrade.py
coverdl/utils.py
coverdl-0.4.3.dist-info/METADATA
coverdl-0.4.3.dist-info/WHEEL
coverdl-0.4.3.dist-info/entry_points.txt
coverdl-0.4.3.dist-info/RECORD
