Metadata-Version: 2.3
Name: coverdl
Version: 0.4.3
Summary: A command-line tool for downloading high quality album cover art
Author: viown
Author-email: 48097677+viown@users.noreply.github.com
Requires-Python: >=3.11,<4.0
Classifier: Programming Language :: Python :: 3
Classifier: Programming Language :: Python :: 3.11
Classifier: Programming Language :: Python :: 3.12
Classifier: Programming Language :: Python :: 3.13
Requires-Dist: click (>=8.1.8,<9.0.0)
Requires-Dist: imagehash (>=4.3.2,<5.0.0)
Requires-Dist: mutagen (>=1.47.0,<2.0.0)
Requires-Dist: pillow (>=11.1.0,<12.0.0)
Requires-Dist: requests (>=2.32.3,<3.0.0)
